unseal/__init__.py
unseal/logit_lense.py
unseal/transformers_util.py
unseal/hooks/__init__.py
unseal/hooks/common_hooks.py
unseal/hooks/commons.py
unseal/hooks/rome_hooks.py
unseal/hooks/util.py
unseal/visuals/__init__.py
unseal/visuals/utils.py
unseal/visuals/streamlit_interfaces/__init__.py
unseal/visuals/streamlit_interfaces/all_layers_single_input.py
unseal/visuals/streamlit_interfaces/commons.py
unseal/visuals/streamlit_interfaces/compare_two_inputs.py
unseal/visuals/streamlit_interfaces/interface_setup.py
unseal/visuals/streamlit_interfaces/load_only.py
unseal/visuals/streamlit_interfaces/single_layer_single_input.py
unseal/visuals/streamlit_interfaces/split_full_model_vis_into_layers.py
unseal/visuals/streamlit_interfaces/utils.py
Unseal-0.2.1.dist-info/LICENSE
Unseal-0.2.1.dist-info/METADATA
Unseal-0.2.1.dist-info/WHEEL
Unseal-0.2.1.dist-info/top_level.txt
Unseal-0.2.1.dist-info/RECORD
